{
  "cpu": "sprhbm",
  "Version": "release",
  "ServiceName": "crashdump",
  "DefaultState": "Enable",
  "UseSections": true,
  "PECIHeaders": {
    "CrashDump_Discovery": ["Target", "Opcode", "Param0", "Param1", "Param2", "ReadLen"],
    "CrashDump_GetFrame": ["Target", "Param0", "Param1", "Param2", "ReadLen"],
    "Ping": ["Target"],
    "GetCPUID": ["Target"],
    "RdIAMSR": ["Target", "Thread", "Address"],
    "RdPkgConfig": ["Target", "Index", "Param", "ReadLen"],
    "RdPCIConfigLocal": ["Target", "Bus", "Dev", "Func", "Reg", "ReadLen"],
    "RdEndPointConfigPciLocal": ["Target", "Seg", "Bus", "Dev", "Func", "Reg", "ReadLen"],
    "WrEndPointPCIConfigLocal": ["Target", "Seg", "Bus", "Dev", "Func", "Reg", "ReadLen", "Value"],
    "RdEndPointConfigMMIO": ["Target", "Seg", "Bus", "Dev", "Func", "Bar", "AType", "Offset", "ReadLen"],
    "Telemetry_Discovery": ["Target", "Opcode", "Param0", "Param1", "Param2", "ReadLen"]
  },
  "Sections": [
    {
      "MCA_UNCORE":{
        "RecordEnable": false,
        "RootAtLevel": 4,
        "OutputPath": "crash_data/PROCESSORS/cpu%d/MCA"
      }
    },
    {
      "MCA_CBO": {
        "RecordEnable": false
      }
    },
    {
      "Uncore_PCI": {
        "RecordEnable": true,
        "RecordType": "0x08",
        "ProductType": "0x6f",
        "Revision": "0x14",
        "SkipOnFail": false,
        "LoopOnCPU": true,
        "MaxTimeSec": 30,
        "OutputPath": "crash_data/PROCESSORS/cpu%d/uncore",
        "PreReq": {
          "PECICmds": []
        },
        "PECICmds": [
          {
            "RdEndpointConfigPCILocal": [
              {"Params": ["Target", 0, 0, 0, 3, "0x9D8", 4], "Output": {"Name": ["B00_D00_F3_0x9d8"]}},
              {"Params": ["Target", 0, 0, 0, 4, "0x200", 4], "Output": {"Name": ["B00_D00_F4_0x200"]}},
              {"Params": ["Target", 0, 0, 0, 4, "0x204", 4], "Output": {"Name": ["B00_D00_F4_0x204"]}},
              {"Params": ["Target", 0, 0, 0, 4, "0x208", 4], "Output": {"Name": ["B00_D00_F4_0x208"]}},
              {"Params": ["Target", 0, 0, 1, 0, "0x104", 4], "Output": {"Name": ["B00_D01_F0_0x104"]}},
              {"Params": ["Target", 0, 0, 2, 0, "0x52", 2], "Output": {"Name": ["B00_D02_F0_0x52"]}},
              {"Params": ["Target", 0, 0, 2, 0, "0x520", 4], "Output": {"Name": ["B00_D02_F0_0x520"]}},
              {"Params": ["Target", 0, 0, 2, 0, "0x764", 4], "Output": {"Name": ["B00_D02_F0_0x764"]}},
              {"Params": ["Target", 0, 0, 2, 0, "0xA38", 4], "Output": {"Name": ["B00_D02_F0_0xa38"]}},
              {"Params": ["Target", 0, 0, 3, 0, "0x52", 2], "Output": {"Name": ["B00_D03_F0_0x52"]}},
              {"Params": ["Target", 0, 0, 3, 0, "0x764", 4], "Output": {"Name": ["B00_D03_F0_0x764"]}},
              {"Params": ["Target", 0, 0, 3, 0, "0xA38", 4], "Output": {"Name": ["B00_D03_F0_0xa38"]}},
              {"Params": ["Target", 0, 0, 4, 0, "0x52", 2], "Output": {"Name": ["B00_D04_F0_0x52"]}},
              {"Params": ["Target", 0, 0, 4, 0, "0x520", 4], "Output": {"Name": ["B00_D04_F0_0x520"]}},
              {"Params": ["Target", 0, 0, 4, 0, "0x764", 4], "Output": {"Name": ["B00_D04_F0_0x764"]}},
              {"Params": ["Target", 0, 0, 4, 0, "0xA38", 4], "Output": {"Name": ["B00_D04_F0_0xa38"]}},
              {"Params": ["Target", 0, 0, 5, 0, "0x52", 2], "Output": {"Name": ["B00_D05_F0_0x52"]}},
              {"Params": ["Target", 0, 0, 5, 0, "0x764", 4], "Output": {"Name": ["B00_D05_F0_0x764"]}},
              {"Params": ["Target", 0, 0, 5, 0, "0xA38", 4], "Output": {"Name": ["B00_D05_F0_0xa38"]}},
              {"Params": ["Target", 0, 0, 6, 0, "0x52", 2], "Output": {"Name": ["B00_D06_F0_0x52"]}},
              {"Params": ["Target", 0, 0, 6, 0, "0x110", 4], "Output": {"Name": ["B00_D06_F0_0x110"]}},
              {"Params": ["Target", 0, 0, 6, 0, "0x520", 4], "Output": {"Name": ["B00_D06_F0_0x520"]}},
              {"Params": ["Target", 0, 0, 6, 0, "0x764", 4], "Output": {"Name": ["B00_D06_F0_0x764"]}},
              {"Params": ["Target", 0, 0, 6, 0, "0xA38", 4], "Output": {"Name": ["B00_D06_F0_0xa38"]}},
              {"Params": ["Target", 0, 0, 7, 0, "0x52", 2], "Output": {"Name": ["B00_D07_F0_0x52"]}},
              {"Params": ["Target", 0, 0, 7, 0, "0x764", 4], "Output": {"Name": ["B00_D07_F0_0x764"]}},
              {"Params": ["Target", 0, 0, 7, 0, "0xA38", 4], "Output": {"Name": ["B00_D07_F0_0xa38"]}},
              {"Params": ["Target", 0, 0, 8, 0, "0x52", 2], "Output": {"Name": ["B00_D08_F0_0x52"]}},
              {"Params": ["Target", 0, 0, 8, 0, "0x104", 4], "Output": {"Name": ["B00_D08_F0_0x104"]}},
              {"Params": ["Target", 0, 0, 8, 0, "0x110", 4], "Output": {"Name": ["B00_D08_F0_0x110"]}},
              {"Params": ["Target", 0, 0, 8, 0, "0x130", 4], "Output": {"Name": ["B00_D08_F0_0x130"]}},
              {"Params": ["Target", 0, 0, 8, 0, "0x520", 4], "Output": {"Name": ["B00_D08_F0_0x520"]}},
              {"Params": ["Target", 0, 0, 8, 0, "0x764", 4], "Output": {"Name": ["B00_D08_F0_0x764"]}},
              {"Params": ["Target", 0, 0, 8, 0, "0xA38", 4], "Output": {"Name": ["B00_D08_F0_0xa38"]}},
              {"Params": ["Target", 0, 1, 0, 3, "0x9D8", 4], "Output": {"Name": ["B01_D00_F3_0x9d8"]}},
              {"Params": ["Target", 0, 1, 0, 4, "0x200", 4], "Output": {"Name": ["B01_D00_F4_0x200"]}},
              {"Params": ["Target", 0, 1, 0, 4, "0x204", 4], "Output": {"Name": ["B01_D00_F4_0x204"]}},
              {"Params": ["Target", 0, 1, 0, 4, "0x208", 4], "Output": {"Name": ["B01_D00_F4_0x208"]}},
              {"Params": ["Target", 0, 1, 1, 0, "0x52", 2], "Output": {"Name": ["B01_D01_F0_0x52"]}},
              {"Params": ["Target", 0, 1, 1, 0, "0x104", 4], "Output": {"Name": ["B01_D01_F0_0x104"]}},
              {"Params": ["Target", 0, 1, 1, 0, "0x520", 4], "Output": {"Name": ["B01_D01_F0_0x520"]}},
              {"Params": ["Target", 0, 1, 1, 0, "0x764", 4], "Output": {"Name": ["B01_D01_F0_0x764"]}},
              {"Params": ["Target", 0, 1, 1, 0, "0xA38", 4], "Output": {"Name": ["B01_D01_F0_0xa38"]}},
              {"Params": ["Target", 0, 1, 2, 0, "0x52", 2], "Output": {"Name": ["B01_D02_F0_0x52"]}},
              {"Params": ["Target", 0, 1, 2, 0, "0x520", 4], "Output": {"Name": ["B01_D02_F0_0x520"]}},
              {"Params": ["Target", 0, 1, 2, 0, "0x764", 4], "Output": {"Name": ["B01_D02_F0_0x764"]}},
              {"Params": ["Target", 0, 1, 2, 0, "0xA38", 4], "Output": {"Name": ["B01_D02_F0_0xa38"]}},
              {"Params": ["Target", 0, 1, 3, 0, "0x52", 2], "Output": {"Name": ["B01_D03_F0_0x52"]}},
              {"Params": ["Target", 0, 1, 3, 0, "0x110", 4], "Output": {"Name": ["B01_D03_F0_0x110"]}},
              {"Params": ["Target", 0, 1, 3, 0, "0x764", 4], "Output": {"Name": ["B01_D03_F0_0x764"]}},
              {"Params": ["Target", 0, 1, 3, 0, "0xA38", 4], "Output": {"Name": ["B01_D03_F0_0xa38"]}},
              {"Params": ["Target", 0, 1, 4, 0, "0x52", 2], "Output": {"Name": ["B01_D04_F0_0x52"]}},
              {"Params": ["Target", 0, 1, 4, 0, "0x520", 4], "Output": {"Name": ["B01_D04_F0_0x520"]}},
              {"Params": ["Target", 0, 1, 4, 0, "0x764", 4], "Output": {"Name": ["B01_D04_F0_0x764"]}},
              {"Params": ["Target", 0, 1, 4, 0, "0xA38", 4], "Output": {"Name": ["B01_D04_F0_0xa38"]}},
              {"Params": ["Target", 0, 1, 5, 0, "0x52", 2], "Output": {"Name": ["B01_D05_F0_0x52"]}},
              {"Params": ["Target", 0, 1, 5, 0, "0x764", 4], "Output": {"Name": ["B01_D05_F0_0x764"]}},
              {"Params": ["Target", 0, 1, 5, 0, "0xA38", 4], "Output": {"Name": ["B01_D05_F0_0xa38"]}},
              {"Params": ["Target", 0, 1, 6, 0, "0x52", 2], "Output": {"Name": ["B01_D06_F0_0x52"]}},
              {"Params": ["Target", 0, 1, 6, 0, "0x110", 4], "Output": {"Name": ["B01_D06_F0_0x110"]}},
              {"Params": ["Target", 0, 1, 6, 0, "0x520", 4], "Output": {"Name": ["B01_D06_F0_0x520"]}},
              {"Params": ["Target", 0, 1, 6, 0, "0x764", 4], "Output": {"Name": ["B01_D06_F0_0x764"]}},
              {"Params": ["Target", 0, 1, 6, 0, "0xA38", 4], "Output": {"Name": ["B01_D06_F0_0xa38"]}},
              {"Params": ["Target", 0, 1, 7, 0, "0x52", 2], "Output": {"Name": ["B01_D07_F0_0x52"]}},
              {"Params": ["Target", 0, 1, 7, 0, "0x764", 4], "Output": {"Name": ["B01_D07_F0_0x764"]}},
              {"Params": ["Target", 0, 1, 7, 0, "0xA38", 4], "Output": {"Name": ["B01_D07_F0_0xa38"]}},
              {"Params": ["Target", 0, 1, 8, 0, "0x52", 2], "Output": {"Name": ["B01_D08_F0_0x52"]}},
              {"Params": ["Target", 0, 1, 8, 0, "0x104", 4], "Output": {"Name": ["B01_D08_F0_0x104"]}},
              {"Params": ["Target", 0, 1, 8, 0, "0x110", 4], "Output": {"Name": ["B01_D08_F0_0x110"]}},
              {"Params": ["Target", 0, 1, 8, 0, "0x520", 4], "Output": {"Name": ["B01_D08_F0_0x520"]}},
              {"Params": ["Target", 0, 1, 8, 0, "0x764", 4], "Output": {"Name": ["B01_D08_F0_0x764"]}},
              {"Params": ["Target", 0, 1, 8, 0, "0xA38", 4], "Output": {"Name": ["B01_D08_F0_0xa38"]}},
              {"Params": ["Target", 0, 2, 0, 3, "0x9D8", 4], "Output": {"Name": ["B02_D00_F3_0x9d8"]}},
              {"Params": ["Target", 0, 2, 0, 4, "0x200", 4], "Output": {"Name": ["B02_D00_F4_0x200"]}},
              {"Params": ["Target", 0, 2, 0, 4, "0x204", 4], "Output": {"Name": ["B02_D00_F4_0x204"]}},
              {"Params": ["Target", 0, 2, 0, 4, "0x208", 4], "Output": {"Name": ["B02_D00_F4_0x208"]}},
              {"Params": ["Target", 0, 2, 1, 0, "0x52", 2], "Output": {"Name": ["B02_D01_F0_0x52"]}},
              {"Params": ["Target", 0, 2, 1, 0, "0x104", 4], "Output": {"Name": ["B02_D01_F0_0x104"]}},
              {"Params": ["Target", 0, 2, 1, 0, "0x110", 4], "Output": {"Name": ["B02_D01_F0_0x110"]}},
              {"Params": ["Target", 0, 2, 1, 0, "0x520", 4], "Output": {"Name": ["B02_D01_F0_0x520"]}},
              {"Params": ["Target", 0, 2, 1, 0, "0x764", 4], "Output": {"Name": ["B02_D01_F0_0x764"]}},
              {"Params": ["Target", 0, 2, 1, 0, "0xA38", 4], "Output": {"Name": ["B02_D01_F0_0xa38"]}},
              {"Params": ["Target", 0, 2, 2, 0, "0x52", 2], "Output": {"Name": ["B02_D02_F0_0x52"]}},
              {"Params": ["Target", 0, 2, 2, 0, "0x110", 4], "Output": {"Name": ["B02_D02_F0_0x110"]}},
              {"Params": ["Target", 0, 2, 2, 0, "0x520", 4], "Output": {"Name": ["B02_D02_F0_0x520"]}},
              {"Params": ["Target", 0, 2, 2, 0, "0x764", 4], "Output": {"Name": ["B02_D02_F0_0x764"]}},
              {"Params": ["Target", 0, 2, 2, 0, "0xA38", 4], "Output": {"Name": ["B02_D02_F0_0xa38"]}},
              {"Params": ["Target", 0, 2, 3, 0, "0x52", 2], "Output": {"Name": ["B02_D03_F0_0x52"]}},
              {"Params": ["Target", 0, 2, 3, 0, "0x110", 4], "Output": {"Name": ["B02_D03_F0_0x110"]}},
              {"Params": ["Target", 0, 2, 3, 0, "0x764", 4], "Output": {"Name": ["B02_D03_F0_0x764"]}},
              {"Params": ["Target", 0, 2, 3, 0, "0xA38", 4], "Output": {"Name": ["B02_D03_F0_0xa38"]}},
              {"Params": ["Target", 0, 2, 4, 0, "0x52", 2], "Output": {"Name": ["B02_D04_F0_0x52"]}},
              {"Params": ["Target", 0, 2, 4, 0, "0x110", 4], "Output": {"Name": ["B02_D04_F0_0x110"]}},
              {"Params": ["Target", 0, 2, 4, 0, "0x520", 4], "Output": {"Name": ["B02_D04_F0_0x520"]}},
              {"Params": ["Target", 0, 2, 4, 0, "0x764", 4], "Output": {"Name": ["B02_D04_F0_0x764"]}},
              {"Params": ["Target", 0, 2, 4, 0, "0xA38", 4], "Output": {"Name": ["B02_D04_F0_0xa38"]}},
              {"Params": ["Target", 0, 2, 5, 0, "0x52", 2], "Output": {"Name": ["B02_D05_F0_0x52"]}},
              {"Params": ["Target", 0, 2, 5, 0, "0x110", 4], "Output": {"Name": ["B02_D05_F0_0x110"]}},
              {"Params": ["Target", 0, 2, 5, 0, "0x764", 4], "Output": {"Name": ["B02_D05_F0_0x764"]}},
              {"Params": ["Target", 0, 2, 5, 0, "0xA38", 4], "Output": {"Name": ["B02_D05_F0_0xa38"]}},
              {"Params": ["Target", 0, 2, 6, 0, "0x52", 2], "Output": {"Name": ["B02_D06_F0_0x52"]}},
              {"Params": ["Target", 0, 2, 6, 0, "0x110", 4], "Output": {"Name": ["B02_D06_F0_0x110"]}},
              {"Params": ["Target", 0, 2, 6, 0, "0x520", 4], "Output": {"Name": ["B02_D06_F0_0x520"]}},
              {"Params": ["Target", 0, 2, 6, 0, "0x764", 4], "Output": {"Name": ["B02_D06_F0_0x764"]}},
              {"Params": ["Target", 0, 2, 6, 0, "0xA38", 4], "Output": {"Name": ["B02_D06_F0_0xa38"]}},
              {"Params": ["Target", 0, 2, 7, 0, "0x52", 2], "Output": {"Name": ["B02_D07_F0_0x52"]}},
              {"Params": ["Target", 0, 2, 7, 0, "0x110", 4], "Output": {"Name": ["B02_D07_F0_0x110"]}},
              {"Params": ["Target", 0, 2, 7, 0, "0x764", 4], "Output": {"Name": ["B02_D07_F0_0x764"]}},
              {"Params": ["Target", 0, 2, 7, 0, "0xA38", 4], "Output": {"Name": ["B02_D07_F0_0xa38"]}},
              {"Params": ["Target", 0, 2, 8, 0, "0x52", 2], "Output": {"Name": ["B02_D08_F0_0x52"]}},
              {"Params": ["Target", 0, 2, 8, 0, "0x104", 4], "Output": {"Name": ["B02_D08_F0_0x104"]}},
              {"Params": ["Target", 0, 2, 8, 0, "0x110", 4], "Output": {"Name": ["B02_D08_F0_0x110"]}},
              {"Params": ["Target", 0, 2, 8, 0, "0x520", 4], "Output": {"Name": ["B02_D08_F0_0x520"]}},
              {"Params": ["Target", 0, 2, 8, 0, "0x764", 4], "Output": {"Name": ["B02_D08_F0_0x764"]}},
              {"Params": ["Target", 0, 2, 8, 0, "0xA38", 4], "Output": {"Name": ["B02_D08_F0_0xa38"]}},
              {"Params": ["Target", 0, 3, 0, 3, "0x9D8", 4], "Output": {"Name": ["B03_D00_F3_0x9d8"]}},
              {"Params": ["Target", 0, 3, 0, 4, "0x200", 4], "Output": {"Name": ["B03_D00_F4_0x200"]}},
              {"Params": ["Target", 0, 3, 0, 4, "0x204", 4], "Output": {"Name": ["B03_D00_F4_0x204"]}},
              {"Params": ["Target", 0, 3, 0, 4, "0x208", 4], "Output": {"Name": ["B03_D00_F4_0x208"]}},
              {"Params": ["Target", 0, 3, 1, 0, "0x52", 2], "Output": {"Name": ["B03_D01_F0_0x52"]}},
              {"Params": ["Target", 0, 3, 1, 0, "0x104", 4], "Output": {"Name": ["B03_D01_F0_0x104"]}},
              {"Params": ["Target", 0, 3, 1, 0, "0x110", 4], "Output": {"Name": ["B03_D01_F0_0x110"]}},
              {"Params": ["Target", 0, 3, 1, 0, "0x520", 4], "Output": {"Name": ["B03_D01_F0_0x520"]}},
              {"Params": ["Target", 0, 3, 1, 0, "0x764", 4], "Output": {"Name": ["B03_D01_F0_0x764"]}},
              {"Params": ["Target", 0, 3, 1, 0, "0xA38", 4], "Output": {"Name": ["B03_D01_F0_0xa38"]}},
              {"Params": ["Target", 0, 3, 2, 0, "0x52", 2], "Output": {"Name": ["B03_D02_F0_0x52"]}},
              {"Params": ["Target", 0, 3, 2, 0, "0x520", 4], "Output": {"Name": ["B03_D02_F0_0x520"]}},
              {"Params": ["Target", 0, 3, 2, 0, "0x764", 4], "Output": {"Name": ["B03_D02_F0_0x764"]}},
              {"Params": ["Target", 0, 3, 2, 0, "0xA38", 4], "Output": {"Name": ["B03_D02_F0_0xa38"]}},
              {"Params": ["Target", 0, 3, 3, 0, "0x52", 2], "Output": {"Name": ["B03_D03_F0_0x52"]}},
              {"Params": ["Target", 0, 3, 3, 0, "0x110", 4], "Output": {"Name": ["B03_D03_F0_0x110"]}},
              {"Params": ["Target", 0, 3, 3, 0, "0x764", 4], "Output": {"Name": ["B03_D03_F0_0x764"]}},
              {"Params": ["Target", 0, 3, 3, 0, "0xA38", 4], "Output": {"Name": ["B03_D03_F0_0xa38"]}},
              {"Params": ["Target", 0, 3, 4, 0, "0x52", 2], "Output": {"Name": ["B03_D04_F0_0x52"]}},
              {"Params": ["Target", 0, 3, 4, 0, "0x520", 4], "Output": {"Name": ["B03_D04_F0_0x520"]}},
              {"Params": ["Target", 0, 3, 4, 0, "0x764", 4], "Output": {"Name": ["B03_D04_F0_0x764"]}},
              {"Params": ["Target", 0, 3, 4, 0, "0xA38", 4], "Output": {"Name": ["B03_D04_F0_0xa38"]}},
              {"Params": ["Target", 0, 3, 5, 0, "0x52", 2], "Output": {"Name": ["B03_D05_F0_0x52"]}},
              {"Params": ["Target", 0, 3, 5, 0, "0x764", 4], "Output": {"Name": ["B03_D05_F0_0x764"]}},
              {"Params": ["Target", 0, 3, 5, 0, "0xA38", 4], "Output": {"Name": ["B03_D05_F0_0xa38"]}},
              {"Params": ["Target", 0, 3, 6, 0, "0x52", 2], "Output": {"Name": ["B03_D06_F0_0x52"]}},
              {"Params": ["Target", 0, 3, 6, 0, "0x110", 4], "Output": {"Name": ["B03_D06_F0_0x110"]}},
              {"Params": ["Target", 0, 3, 6, 0, "0x520", 4], "Output": {"Name": ["B03_D06_F0_0x520"]}},
              {"Params": ["Target", 0, 3, 6, 0, "0x764", 4], "Output": {"Name": ["B03_D06_F0_0x764"]}},
              {"Params": ["Target", 0, 3, 6, 0, "0xA38", 4], "Output": {"Name": ["B03_D06_F0_0xa38"]}},
              {"Params": ["Target", 0, 3, 7, 0, "0x52", 2], "Output": {"Name": ["B03_D07_F0_0x52"]}},
              {"Params": ["Target", 0, 3, 7, 0, "0x764", 4], "Output": {"Name": ["B03_D07_F0_0x764"]}},
              {"Params": ["Target", 0, 3, 7, 0, "0xA38", 4], "Output": {"Name": ["B03_D07_F0_0xa38"]}},
              {"Params": ["Target", 0, 3, 8, 0, "0x52", 2], "Output": {"Name": ["B03_D08_F0_0x52"]}},
              {"Params": ["Target", 0, 3, 8, 0, "0x104", 4], "Output": {"Name": ["B03_D08_F0_0x104"]}},
              {"Params": ["Target", 0, 3, 8, 0, "0x110", 4], "Output": {"Name": ["B03_D08_F0_0x110"]}},
              {"Params": ["Target", 0, 3, 8, 0, "0x520", 4], "Output": {"Name": ["B03_D08_F0_0x520"]}},
              {"Params": ["Target", 0, 3, 8, 0, "0x764", 4], "Output": {"Name": ["B03_D08_F0_0x764"]}},
              {"Params": ["Target", 0, 3, 8, 0, "0xA38", 4], "Output": {"Name": ["B03_D08_F0_0xa38"]}},
              {"Params": ["Target", 0, 4, 0, 3, "0x9D8", 4], "Output": {"Name": ["B04_D00_F3_0x9d8"]}},
              {"Params": ["Target", 0, 4, 0, 4, "0x200", 4], "Output": {"Name": ["B04_D00_F4_0x200"]}},
              {"Params": ["Target", 0, 4, 0, 4, "0x204", 4], "Output": {"Name": ["B04_D00_F4_0x204"]}},
              {"Params": ["Target", 0, 4, 0, 4, "0x208", 4], "Output": {"Name": ["B04_D00_F4_0x208"]}},
              {"Params": ["Target", 0, 4, 1, 0, "0x52", 2], "Output": {"Name": ["B04_D01_F0_0x52"]}},
              {"Params": ["Target", 0, 4, 1, 0, "0x104", 4], "Output": {"Name": ["B04_D01_F0_0x104"]}},
              {"Params": ["Target", 0, 4, 1, 0, "0x110", 4], "Output": {"Name": ["B04_D01_F0_0x110"]}},
              {"Params": ["Target", 0, 4, 1, 0, "0x520", 4], "Output": {"Name": ["B04_D01_F0_0x520"]}},
              {"Params": ["Target", 0, 4, 1, 0, "0x764", 4], "Output": {"Name": ["B04_D01_F0_0x764"]}},
              {"Params": ["Target", 0, 4, 1, 0, "0xA38", 4], "Output": {"Name": ["B04_D01_F0_0xa38"]}},
              {"Params": ["Target", 0, 4, 2, 0, "0x52", 2], "Output": {"Name": ["B04_D02_F0_0x52"]}},
              {"Params": ["Target", 0, 4, 2, 0, "0x520", 4], "Output": {"Name": ["B04_D02_F0_0x520"]}},
              {"Params": ["Target", 0, 4, 2, 0, "0x764", 4], "Output": {"Name": ["B04_D02_F0_0x764"]}},
              {"Params": ["Target", 0, 4, 2, 0, "0xA38", 4], "Output": {"Name": ["B04_D02_F0_0xa38"]}},
              {"Params": ["Target", 0, 4, 3, 0, "0x52", 2], "Output": {"Name": ["B04_D03_F0_0x52"]}},
              {"Params": ["Target", 0, 4, 3, 0, "0x110", 4], "Output": {"Name": ["B04_D03_F0_0x110"]}},
              {"Params": ["Target", 0, 4, 3, 0, "0x764", 4], "Output": {"Name": ["B04_D03_F0_0x764"]}},
              {"Params": ["Target", 0, 4, 3, 0, "0xA38", 4], "Output": {"Name": ["B04_D03_F0_0xa38"]}},
              {"Params": ["Target", 0, 4, 4, 0, "0x52", 2], "Output": {"Name": ["B04_D04_F0_0x52"]}},
              {"Params": ["Target", 0, 4, 4, 0, "0x520", 4], "Output": {"Name": ["B04_D04_F0_0x520"]}},
              {"Params": ["Target", 0, 4, 4, 0, "0x764", 4], "Output": {"Name": ["B04_D04_F0_0x764"]}},
              {"Params": ["Target", 0, 4, 4, 0, "0xA38", 4], "Output": {"Name": ["B04_D04_F0_0xa38"]}},
              {"Params": ["Target", 0, 4, 5, 0, "0x52", 2], "Output": {"Name": ["B04_D05_F0_0x52"]}},
              {"Params": ["Target", 0, 4, 5, 0, "0x764", 4], "Output": {"Name": ["B04_D05_F0_0x764"]}},
              {"Params": ["Target", 0, 4, 5, 0, "0xA38", 4], "Output": {"Name": ["B04_D05_F0_0xa38"]}},
              {"Params": ["Target", 0, 4, 6, 0, "0x52", 2], "Output": {"Name": ["B04_D06_F0_0x52"]}},
              {"Params": ["Target", 0, 4, 6, 0, "0x110", 4], "Output": {"Name": ["B04_D06_F0_0x110"]}},
              {"Params": ["Target", 0, 4, 6, 0, "0x520", 4], "Output": {"Name": ["B04_D06_F0_0x520"]}},
              {"Params": ["Target", 0, 4, 6, 0, "0x764", 4], "Output": {"Name": ["B04_D06_F0_0x764"]}},
              {"Params": ["Target", 0, 4, 6, 0, "0xA38", 4], "Output": {"Name": ["B04_D06_F0_0xa38"]}},
              {"Params": ["Target", 0, 4, 7, 0, "0x52", 2], "Output": {"Name": ["B04_D07_F0_0x52"]}},
              {"Params": ["Target", 0, 4, 7, 0, "0x764", 4], "Output": {"Name": ["B04_D07_F0_0x764"]}},
              {"Params": ["Target", 0, 4, 7, 0, "0xA38", 4], "Output": {"Name": ["B04_D07_F0_0xa38"]}},
              {"Params": ["Target", 0, 4, 8, 0, "0x52", 2], "Output": {"Name": ["B04_D08_F0_0x52"]}},
              {"Params": ["Target", 0, 4, 8, 0, "0x104", 4], "Output": {"Name": ["B04_D08_F0_0x104"]}},
              {"Params": ["Target", 0, 4, 8, 0, "0x110", 4], "Output": {"Name": ["B04_D08_F0_0x110"]}},
              {"Params": ["Target", 0, 4, 8, 0, "0x520", 4], "Output": {"Name": ["B04_D08_F0_0x520"]}},
              {"Params": ["Target", 0, 4, 8, 0, "0x764", 4], "Output": {"Name": ["B04_D08_F0_0x764"]}},
              {"Params": ["Target", 0, 4, 8, 0, "0xA38", 4], "Output": {"Name": ["B04_D08_F0_0xa38"]}},
              {"Params": ["Target", 0, 5, 0, 3, "0x9D8", 4], "Output": {"Name": ["B05_D00_F3_0x9d8"]}},
              {"Params": ["Target", 0, 5, 0, 4, "0x200", 4], "Output": {"Name": ["B05_D00_F4_0x200"]}},
              {"Params": ["Target", 0, 5, 0, 4, "0x204", 4], "Output": {"Name": ["B05_D00_F4_0x204"]}},
              {"Params": ["Target", 0, 5, 0, 4, "0x208", 4], "Output": {"Name": ["B05_D00_F4_0x208"]}},
              {"Params": ["Target", 0, 5, 1, 0, "0x52", 2], "Output": {"Name": ["B05_D01_F0_0x52"]}},
              {"Params": ["Target", 0, 5, 1, 0, "0x104", 4], "Output": {"Name": ["B05_D01_F0_0x104"]}},
              {"Params": ["Target", 0, 5, 1, 0, "0x110", 4], "Output": {"Name": ["B05_D01_F0_0x110"]}},
              {"Params": ["Target", 0, 5, 1, 0, "0x520", 4], "Output": {"Name": ["B05_D01_F0_0x520"]}},
              {"Params": ["Target", 0, 5, 1, 0, "0x764", 4], "Output": {"Name": ["B05_D01_F0_0x764"]}},
              {"Params": ["Target", 0, 5, 1, 0, "0xA38", 4], "Output": {"Name": ["B05_D01_F0_0xa38"]}},
              {"Params": ["Target", 0, 5, 2, 0, "0x52", 2], "Output": {"Name": ["B05_D02_F0_0x52"]}},
              {"Params": ["Target", 0, 5, 2, 0, "0x110", 4], "Output": {"Name": ["B05_D02_F0_0x110"]}},
              {"Params": ["Target", 0, 5, 2, 0, "0x520", 4], "Output": {"Name": ["B05_D02_F0_0x520"]}},
              {"Params": ["Target", 0, 5, 2, 0, "0x764", 4], "Output": {"Name": ["B05_D02_F0_0x764"]}},
              {"Params": ["Target", 0, 5, 2, 0, "0xA38", 4], "Output": {"Name": ["B05_D02_F0_0xa38"]}},
              {"Params": ["Target", 0, 5, 3, 0, "0x52", 2], "Output": {"Name": ["B05_D03_F0_0x52"]}},
              {"Params": ["Target", 0, 5, 3, 0, "0x110", 4], "Output": {"Name": ["B05_D03_F0_0x110"]}},
              {"Params": ["Target", 0, 5, 3, 0, "0x764", 4], "Output": {"Name": ["B05_D03_F0_0x764"]}},
              {"Params": ["Target", 0, 5, 3, 0, "0xA38", 4], "Output": {"Name": ["B05_D03_F0_0xa38"]}},
              {"Params": ["Target", 0, 5, 4, 0, "0x52", 2], "Output": {"Name": ["B05_D04_F0_0x52"]}},
              {"Params": ["Target", 0, 5, 4, 0, "0x110", 4], "Output": {"Name": ["B05_D04_F0_0x110"]}},
              {"Params": ["Target", 0, 5, 4, 0, "0x520", 4], "Output": {"Name": ["B05_D04_F0_0x520"]}},
              {"Params": ["Target", 0, 5, 4, 0, "0x764", 4], "Output": {"Name": ["B05_D04_F0_0x764"]}},
              {"Params": ["Target", 0, 5, 4, 0, "0xA38", 4], "Output": {"Name": ["B05_D04_F0_0xa38"]}},
              {"Params": ["Target", 0, 5, 5, 0, "0x52", 2], "Output": {"Name": ["B05_D05_F0_0x52"]}},
              {"Params": ["Target", 0, 5, 5, 0, "0x110", 4], "Output": {"Name": ["B05_D05_F0_0x110"]}},
              {"Params": ["Target", 0, 5, 5, 0, "0x764", 4], "Output": {"Name": ["B05_D05_F0_0x764"]}},
              {"Params": ["Target", 0, 5, 5, 0, "0xA38", 4], "Output": {"Name": ["B05_D05_F0_0xa38"]}},
              {"Params": ["Target", 0, 5, 6, 0, "0x52", 2], "Output": {"Name": ["B05_D06_F0_0x52"]}},
              {"Params": ["Target", 0, 5, 6, 0, "0x110", 4], "Output": {"Name": ["B05_D06_F0_0x110"]}},
              {"Params": ["Target", 0, 5, 6, 0, "0x520", 4], "Output": {"Name": ["B05_D06_F0_0x520"]}},
              {"Params": ["Target", 0, 5, 6, 0, "0x764", 4], "Output": {"Name": ["B05_D06_F0_0x764"]}},
              {"Params": ["Target", 0, 5, 6, 0, "0xA38", 4], "Output": {"Name": ["B05_D06_F0_0xa38"]}},
              {"Params": ["Target", 0, 5, 7, 0, "0x52", 2], "Output": {"Name": ["B05_D07_F0_0x52"]}},
              {"Params": ["Target", 0, 5, 7, 0, "0x110", 4], "Output": {"Name": ["B05_D07_F0_0x110"]}},
              {"Params": ["Target", 0, 5, 7, 0, "0x764", 4], "Output": {"Name": ["B05_D07_F0_0x764"]}},
              {"Params": ["Target", 0, 5, 7, 0, "0xA38", 4], "Output": {"Name": ["B05_D07_F0_0xa38"]}},
              {"Params": ["Target", 0, 5, 8, 0, "0x52", 2], "Output": {"Name": ["B05_D08_F0_0x52"]}},
              {"Params": ["Target", 0, 5, 8, 0, "0x104", 4], "Output": {"Name": ["B05_D08_F0_0x104"]}},
              {"Params": ["Target", 0, 5, 8, 0, "0x110", 4], "Output": {"Name": ["B05_D08_F0_0x110"]}},
              {"Params": ["Target", 0, 5, 8, 0, "0x520", 4], "Output": {"Name": ["B05_D08_F0_0x520"]}},
              {"Params": ["Target", 0, 5, 8, 0, "0x764", 4], "Output": {"Name": ["B05_D08_F0_0x764"]}},
              {"Params": ["Target", 0, 5, 8, 0, "0xA38", 4], "Output": {"Name": ["B05_D08_F0_0xa38"]}},
              {"Params": ["Target", 0, 6, 0, 4, "0x200", 4], "Output": {"Name": ["B06_D00_F4_0x200"]}},
              {"Params": ["Target", 0, 6, 0, 4, "0x204", 4], "Output": {"Name": ["B06_D00_F4_0x204"]}},
              {"Params": ["Target", 0, 6, 0, 4, "0x208", 4], "Output": {"Name": ["B06_D00_F4_0x208"]}},
              {"Params": ["Target", 0, 7, 0, 4, "0x200", 4], "Output": {"Name": ["B07_D00_F4_0x200"]}},
              {"Params": ["Target", 0, 7, 0, 4, "0x204", 4], "Output": {"Name": ["B07_D00_F4_0x204"]}},
              {"Params": ["Target", 0, 7, 0, 4, "0x208", 4], "Output": {"Name": ["B07_D00_F4_0x208"]}},
              {"Params": ["Target", 0, 8, 0, 4, "0x200", 4], "Output": {"Name": ["B08_D00_F4_0x200"]}},
              {"Params": ["Target", 0, 8, 0, 4, "0x204", 4], "Output": {"Name": ["B08_D00_F4_0x204"]}},
              {"Params": ["Target", 0, 8, 0, 4, "0x208", 4], "Output": {"Name": ["B08_D00_F4_0x208"]}},
              {"Params": ["Target", 0, 8, 1, 0, "0x4A", 2], "Output": {"Name": ["B08_D01_F0_0x4a"]}},
              {"Params": ["Target", 0, 8, 1, 0, "0x104", 4], "Output": {"Name": ["B08_D01_F0_0x104"]}},
              {"Params": ["Target", 0, 8, 1, 0, "0x110", 4], "Output": {"Name": ["B08_D01_F0_0x110"]}},
              {"Params": ["Target", 0, 8, 1, 0, "0x528", 4], "Output": {"Name": ["B08_D01_F0_0x528"]}},
              {"Params": ["Target", 0, 9, 0, 4, "0x200", 4], "Output": {"Name": ["B09_D00_F4_0x200"]}},
              {"Params": ["Target", 0, 9, 0, 4, "0x204", 4], "Output": {"Name": ["B09_D00_F4_0x204"]}},
              {"Params": ["Target", 0, 9, 0, 4, "0x208", 4], "Output": {"Name": ["B09_D00_F4_0x208"]}},
              {"Params": ["Target", 0, 9, 1, 0, "0x4A", 2], "Output": {"Name": ["B09_D01_F0_0x4a"]}},
              {"Params": ["Target", 0, 9, 1, 0, "0x104", 4], "Output": {"Name": ["B09_D01_F0_0x104"]}},
              {"Params": ["Target", 0, 9, 1, 0, "0x110", 4], "Output": {"Name": ["B09_D01_F0_0x110"]}},
              {"Params": ["Target", 0, 9, 1, 0, "0x528", 4], "Output": {"Name": ["B09_D01_F0_0x528"]}},
              {"Params": ["Target", 0, 10, 0, 4, "0x200", 4], "Output": {"Name": ["B10_D00_F4_0x200"]}},
              {"Params": ["Target", 0, 10, 0, 4, "0x204", 4], "Output": {"Name": ["B10_D00_F4_0x204"]}},
              {"Params": ["Target", 0, 10, 0, 4, "0x208", 4], "Output": {"Name": ["B10_D00_F4_0x208"]}},
              {"Params": ["Target", 0, 10, 1, 0, "0x4A", 2], "Output": {"Name": ["B10_D01_F0_0x4a"]}},
              {"Params": ["Target", 0, 10, 1, 0, "0x104", 4], "Output": {"Name": ["B10_D01_F0_0x104"]}},
              {"Params": ["Target", 0, 10, 1, 0, "0x110", 4], "Output": {"Name": ["B10_D01_F0_0x110"]}},
              {"Params": ["Target", 0, 10, 1, 0, "0x528", 4], "Output": {"Name": ["B10_D01_F0_0x528"]}},
              {"Params": ["Target", 0, 11, 0, 4, "0x200", 4], "Output": {"Name": ["B11_D00_F4_0x200"]}},
              {"Params": ["Target", 0, 11, 0, 4, "0x204", 4], "Output": {"Name": ["B11_D00_F4_0x204"]}},
              {"Params": ["Target", 0, 11, 0, 4, "0x208", 4], "Output": {"Name": ["B11_D00_F4_0x208"]}},
              {"Params": ["Target", 0, 11, 1, 0, "0x4A", 2], "Output": {"Name": ["B11_D01_F0_0x4a"]}},
              {"Params": ["Target", 0, 11, 1, 0, "0x104", 4], "Output": {"Name": ["B11_D01_F0_0x104"]}},
              {"Params": ["Target", 0, 11, 1, 0, "0x110", 4], "Output": {"Name": ["B11_D01_F0_0x110"]}},
              {"Params": ["Target", 0, 11, 1, 0, "0x528", 4], "Output": {"Name": ["B11_D01_F0_0x528"]}},
              {"Params": ["Target", 0, 30, 0, 0, "0xA0", 4], "Output": {"Name": ["B30_D00_F0_0xa0"]}},
              {"Params": ["Target", 0, 30, 0, 0, "0xA4", 4], "Output": {"Name": ["B30_D00_F0_0xa4"]}},
              {"Params": ["Target", 0, 30, 0, 0, "0xA8", 4], "Output": {"Name": ["B30_D00_F0_0xa8"]}},
              {"Params": ["Target", 0, 30, 0, 0, "0xE4", 4], "Output": {"Name": ["B30_D00_F0_0xe4"]}},
              {"Params": ["Target", 0, 30, 1, 0, "0x304", 4], "Output": {"Name": ["B30_D01_F0_0x304"]}},
              {"Params": ["Target", 0, 30, 1, 1, "0x6", 2], "Output": {"Name": ["B30_D01_F1_0x6"]}},
              {"Params": ["Target", 0, 30, 2, 0, "0x304", 4], "Output": {"Name": ["B30_D02_F0_0x304"]}},
              {"Params": ["Target", 0, 30, 2, 1, "0x6", 2], "Output": {"Name": ["B30_D02_F1_0x6"]}},
              {"Params": ["Target", 0, 30, 3, 0, "0x304", 4], "Output": {"Name": ["B30_D03_F0_0x304"]}},
              {"Params": ["Target", 0, 30, 3, 1, "0x6", 2], "Output": {"Name": ["B30_D03_F1_0x6"]}},
              {"Params": ["Target", 0, 30, 4, 0, "0x304", 4], "Output": {"Name": ["B30_D04_F0_0x304"]}},
              {"Params": ["Target", 0, 30, 4, 1, "0xA8", 8], "Output": {"Name": ["B30_D04_F1_0xa8"]}},
              {"Params": ["Target", 0, 30, 12, 0, "0x1A0", 4], "Output": {"Name": ["B30_D12_F0_0x1a0"]}},
              {"Params": ["Target", 0, 30, 13, 0, "0x1A0", 4], "Output": {"Name": ["B30_D13_F0_0x1a0"]}},
              {"Params": ["Target", 0, 30, 14, 0, "0x1A0", 4], "Output": {"Name": ["B30_D14_F0_0x1a0"]}},
              {"Params": ["Target", 0, 30, 15, 0, "0x1A0", 4], "Output": {"Name": ["B30_D15_F0_0x1a0"]}},
              {"Params": ["Target", 0, 31, 0, 0, "0x260", 4], "Output": {"Name": ["B31_D00_F0_0x260"]}},
              {"Params": ["Target", 0, 31, 0, 1, "0x260", 4], "Output": {"Name": ["B31_D00_F1_0x260"]}},
              {"Params": ["Target", 0, 31, 0, 2, "0x260", 4], "Output": {"Name": ["B31_D00_F2_0x260"]}},
              {"Params": ["Target", 0, 31, 0, 3, "0x260", 4], "Output": {"Name": ["B31_D00_F3_0x260"]}},
              {"Params": ["Target", 0, 31, 0, 4, "0x260", 4], "Output": {"Name": ["B31_D00_F4_0x260"]}},
              {"Params": ["Target", 0, 31, 0, 5, "0x260", 4], "Output": {"Name": ["B31_D00_F5_0x260"]}},
              {"Params": ["Target", 0, 31, 0, 6, "0x260", 4], "Output": {"Name": ["B31_D00_F6_0x260"]}},
              {"Params": ["Target", 0, 31, 0, 7, "0x260", 4], "Output": {"Name": ["B31_D00_F7_0x260"]}},
              {"Params": ["Target", 0, 31, 1, 0, "0x260", 4], "Output": {"Name": ["B31_D01_F0_0x260"]}},
              {"Params": ["Target", 0, 31, 1, 1, "0x260", 4], "Output": {"Name": ["B31_D01_F1_0x260"]}},
              {"Params": ["Target", 0, 31, 1, 2, "0x260", 4], "Output": {"Name": ["B31_D01_F2_0x260"]}},
              {"Params": ["Target", 0, 31, 1, 3, "0x260", 4], "Output": {"Name": ["B31_D01_F3_0x260"]}},
              {"Params": ["Target", 0, 31, 1, 4, "0x260", 4], "Output": {"Name": ["B31_D01_F4_0x260"]}},
              {"Params": ["Target", 0, 31, 1, 5, "0x260", 4], "Output": {"Name": ["B31_D01_F5_0x260"]}},
              {"Params": ["Target", 0, 31, 1, 6, "0x260", 4], "Output": {"Name": ["B31_D01_F6_0x260"]}},
              {"Params": ["Target", 0, 31, 1, 7, "0x260", 4], "Output": {"Name": ["B31_D01_F7_0x260"]}},
              {"Params": ["Target", 0, 31, 2, 0, "0x260", 4], "Output": {"Name": ["B31_D02_F0_0x260"]}},
              {"Params": ["Target", 0, 31, 2, 1, "0x260", 4], "Output": {"Name": ["B31_D02_F1_0x260"]}},
              {"Params": ["Target", 0, 31, 2, 2, "0x260", 4], "Output": {"Name": ["B31_D02_F2_0x260"]}},
              {"Params": ["Target", 0, 31, 2, 3, "0x260", 4], "Output": {"Name": ["B31_D02_F3_0x260"]}},
              {"Params": ["Target", 0, 31, 2, 4, "0x260", 4], "Output": {"Name": ["B31_D02_F4_0x260"]}},
              {"Params": ["Target", 0, 31, 2, 5, "0x260", 4], "Output": {"Name": ["B31_D02_F5_0x260"]}},
              {"Params": ["Target", 0, 31, 2, 6, "0x260", 4], "Output": {"Name": ["B31_D02_F6_0x260"]}},
              {"Params": ["Target", 0, 31, 2, 7, "0x260", 4], "Output": {"Name": ["B31_D02_F7_0x260"]}},
              {"Params": ["Target", 0, 31, 3, 0, "0x260", 4], "Output": {"Name": ["B31_D03_F0_0x260"]}},
              {"Params": ["Target", 0, 31, 3, 1, "0x260", 4], "Output": {"Name": ["B31_D03_F1_0x260"]}},
              {"Params": ["Target", 0, 31, 3, 2, "0x260", 4], "Output": {"Name": ["B31_D03_F2_0x260"]}},
              {"Params": ["Target", 0, 31, 3, 3, "0x260", 4], "Output": {"Name": ["B31_D03_F3_0x260"]}},
              {"Params": ["Target", 0, 31, 3, 4, "0x260", 4], "Output": {"Name": ["B31_D03_F4_0x260"]}},
              {"Params": ["Target", 0, 31, 3, 5, "0x260", 4], "Output": {"Name": ["B31_D03_F5_0x260"]}},
              {"Params": ["Target", 0, 31, 3, 6, "0x260", 4], "Output": {"Name": ["B31_D03_F6_0x260"]}},
              {"Params": ["Target", 0, 31, 3, 7, "0x260", 4], "Output": {"Name": ["B31_D03_F7_0x260"]}},
              {"Params": ["Target", 0, 31, 4, 0, "0x260", 4], "Output": {"Name": ["B31_D04_F0_0x260"]}},
              {"Params": ["Target", 0, 31, 4, 1, "0x260", 4], "Output": {"Name": ["B31_D04_F1_0x260"]}},
              {"Params": ["Target", 0, 31, 4, 2, "0x260", 4], "Output": {"Name": ["B31_D04_F2_0x260"]}},
              {"Params": ["Target", 0, 31, 4, 3, "0x260", 4], "Output": {"Name": ["B31_D04_F3_0x260"]}},
              {"Params": ["Target", 0, 31, 4, 4, "0x260", 4], "Output": {"Name": ["B31_D04_F4_0x260"]}},
              {"Params": ["Target", 0, 31, 4, 5, "0x260", 4], "Output": {"Name": ["B31_D04_F5_0x260"]}},
              {"Params": ["Target", 0, 31, 4, 6, "0x260", 4], "Output": {"Name": ["B31_D04_F6_0x260"]}},
              {"Params": ["Target", 0, 31, 4, 7, "0x260", 4], "Output": {"Name": ["B31_D04_F7_0x260"]}},
              {"Params": ["Target", 0, 31, 5, 0, "0x260", 4], "Output": {"Name": ["B31_D05_F0_0x260"]}},
              {"Params": ["Target", 0, 31, 5, 1, "0x260", 4], "Output": {"Name": ["B31_D05_F1_0x260"]}},
              {"Params": ["Target", 0, 31, 5, 2, "0x260", 4], "Output": {"Name": ["B31_D05_F2_0x260"]}},
              {"Params": ["Target", 0, 31, 5, 3, "0x260", 4], "Output": {"Name": ["B31_D05_F3_0x260"]}},
              {"Params": ["Target", 0, 31, 5, 4, "0x260", 4], "Output": {"Name": ["B31_D05_F4_0x260"]}},
              {"Params": ["Target", 0, 31, 5, 5, "0x260", 4], "Output": {"Name": ["B31_D05_F5_0x260"]}},
              {"Params": ["Target", 0, 31, 5, 6, "0x260", 4], "Output": {"Name": ["B31_D05_F6_0x260"]}},
              {"Params": ["Target", 0, 31, 5, 7, "0x260", 4], "Output": {"Name": ["B31_D05_F7_0x260"]}},
              {"Params": ["Target", 0, 31, 6, 0, "0x260", 4], "Output": {"Name": ["B31_D06_F0_0x260"]}},
              {"Params": ["Target", 0, 31, 6, 1, "0x260", 4], "Output": {"Name": ["B31_D06_F1_0x260"]}},
              {"Params": ["Target", 0, 31, 6, 2, "0x260", 4], "Output": {"Name": ["B31_D06_F2_0x260"]}},
              {"Params": ["Target", 0, 31, 6, 3, "0x260", 4], "Output": {"Name": ["B31_D06_F3_0x260"]}},
              {"Params": ["Target", 0, 31, 6, 4, "0x260", 4], "Output": {"Name": ["B31_D06_F4_0x260"]}},
              {"Params": ["Target", 0, 31, 6, 5, "0x260", 4], "Output": {"Name": ["B31_D06_F5_0x260"]}},
              {"Params": ["Target", 0, 31, 6, 6, "0x260", 4], "Output": {"Name": ["B31_D06_F6_0x260"]}},
              {"Params": ["Target", 0, 31, 6, 7, "0x260", 4], "Output": {"Name": ["B31_D06_F7_0x260"]}},
              {"Params": ["Target", 0, 31, 7, 0, "0x260", 4], "Output": {"Name": ["B31_D07_F0_0x260"]}},
              {"Params": ["Target", 0, 31, 7, 1, "0x260", 4], "Output": {"Name": ["B31_D07_F1_0x260"]}},
              {"Params": ["Target", 0, 31, 7, 2, "0x260", 4], "Output": {"Name": ["B31_D07_F2_0x260"]}},
              {"Params": ["Target", 0, 31, 7, 3, "0x260", 4], "Output": {"Name": ["B31_D07_F3_0x260"]}},
              {"Params": ["Target", 0, 31, 30, 0, "0x90", 4], "Output": {"Name": ["B31_D30_F0_0x90"]}},
              {"Params": ["Target", 0, 31, 30, 0, "0xBC", 4], "Output": {"Name": ["B31_D30_F0_0xbc"]}},
              {"Params": ["Target", 0, 31, 30, 0, "0xC8", 4], "Output": {"Name": ["B31_D30_F0_0xc8"]}},
              {"Params": ["Target", 0, 31, 30, 0, "0xCC", 4], "Output": {"Name": ["B31_D30_F0_0xcc"]}},
              {"Params": ["Target", 0, 31, 30, 2, "0x80", 4], "Output": {"Name": ["B31_D30_F2_0x80"]}},
              {"Params": ["Target", 0, 31, 30, 2, "0x84", 4], "Output": {"Name": ["B31_D30_F2_0x84"]}},
              {"Params": ["Target", 0, 31, 30, 2, "0x88", 4], "Output": {"Name": ["B31_D30_F2_0x88"]}},
              {"Params": ["Target", 0, 31, 30, 2, "0xC8", 4], "Output": {"Name": ["B31_D30_F2_0xc8"]}},
              {"Params": ["Target", 0, 31, 30, 2, "0xCC", 4], "Output": {"Name": ["B31_D30_F2_0xcc"]}},
              {"Params": ["Target", 0, 31, 30, 2, "0xD0", 4], "Output": {"Name": ["B31_D30_F2_0xd0"]}},
              {"Params": ["Target", 0, 31, 30, 2, "0xD4", 4], "Output": {"Name": ["B31_D30_F2_0xd4"]}},
              {"Params": ["Target", 0, 31, 30, 2, "0xD8", 4], "Output": {"Name": ["B31_D30_F2_0xd8"]}},
              {"Params": ["Target", 0, 31, 30, 6, "0x90", 4], "Output": {"Name": ["B31_D30_F6_0x90"]}},
              {"Params": ["Target", 0, 31, 30, 6, "0x94", 4], "Output": {"Name": ["B31_D30_F6_0x94"]}},
              {"Params": ["Target", 0, 31, 30, 0, "0x90", 4], "Output": {"Name": ["B31_D30_F0_0x90"]}},
              {"Params": ["Target", 0, 0, 0, 1, "0x144", 4], "Output": {"Name": ["B00_D00_F1_0x144"]}},
              {"Params": ["Target", 0, 1, 0, 1, "0x144", 4], "Output": {"Name": ["B01_D00_F1_0x144"]}},
              {"Params": ["Target", 0, 2, 0, 1, "0x144", 4], "Output": {"Name": ["B02_D00_F1_0x144"]}},
              {"Params": ["Target", 0, 3, 0, 1, "0x144", 4], "Output": {"Name": ["B03_D00_F1_0x144"]}},
              {"Params": ["Target", 0, 4, 0, 1, "0x144", 4], "Output": {"Name": ["B04_D00_F1_0x144"]}},
              {"Params": ["Target", 0, 5, 0, 1, "0x144", 4], "Output": {"Name": ["B05_D00_F1_0x144"]}},
              {"Params": ["Target", 0, 6, 0, 1, "0x144", 4], "Output": {"Name": ["B06_D00_F1_0x144"]}},
              {"Params": ["Target", 0, 7, 0, 1, "0x144", 4], "Output": {"Name": ["B07_D00_F1_0x144"]}},
              {"Params": ["Target", 0, 8, 0, 1, "0x144", 4], "Output": {"Name": ["B08_D00_F1_0x144"]}},
              {"Params": ["Target", 0, 9, 0, 1, "0x144", 4], "Output": {"Name": ["B09_D00_F1_0x144"]}},
              {"Params": ["Target", 0, 10, 0, 1, "0x144", 4], "Output": {"Name": ["B10_D00_F1_0x144"]}},
              {"Params": ["Target", 0, 11, 0, 1, "0x144", 4], "Output": {"Name": ["B11_D00_F1_0x144"]}},
              {"Params": ["Target", 0, 30, 1, 0, "0xD4", 4], "Output": {"Name": ["B30_D01_F0_0xd4"]}},
              {"Params": ["Target", 0, 30, 1, 1, "0xA8", 8], "Output": {"Name": ["B30_D01_F1_0xa8"]}},
              {"Params": ["Target", 0, 30, 1, 1, "0x108", 4], "Output": {"Name": ["B30_D01_F1_0x108"]}},
              {"Params": ["Target", 0, 30, 1, 1, "0x10C", 4], "Output": {"Name": ["B30_D01_F1_0x10c"]}},
              {"Params": ["Target", 0, 30, 1, 1, "0x110", 4], "Output": {"Name": ["B30_D01_F1_0x110"]}},
              {"Params": ["Target", 0, 30, 1, 1, "0x114", 4], "Output": {"Name": ["B30_D01_F1_0x114"]}},
              {"Params": ["Target", 0, 30, 1, 1, "0x118", 4], "Output": {"Name": ["B30_D01_F1_0x118"]}},
              {"Params": ["Target", 0, 30, 1, 1, "0x11C", 4], "Output": {"Name": ["B30_D01_F1_0x11c"]}},
              {"Params": ["Target", 0, 30, 2, 0, "0xD4", 4], "Output": {"Name": ["B30_D02_F0_0xd4"]}},
              {"Params": ["Target", 0, 30, 2, 1, "0xA8", 8], "Output": {"Name": ["B30_D02_F1_0xa8"]}},
              {"Params": ["Target", 0, 30, 2, 1, "0x108", 4], "Output": {"Name": ["B30_D02_F1_0x108"]}},
              {"Params": ["Target", 0, 30, 2, 1, "0x10C", 4], "Output": {"Name": ["B30_D02_F1_0x10c"]}},
              {"Params": ["Target", 0, 30, 2, 1, "0x110", 4], "Output": {"Name": ["B30_D02_F1_0x110"]}},
              {"Params": ["Target", 0, 30, 2, 1, "0x114", 4], "Output": {"Name": ["B30_D02_F1_0x114"]}},
              {"Params": ["Target", 0, 30, 2, 1, "0x118", 4], "Output": {"Name": ["B30_D02_F1_0x118"]}},
              {"Params": ["Target", 0, 30, 2, 1, "0x11C", 4], "Output": {"Name": ["B30_D02_F1_0x11c"]}},
              {"Params": ["Target", 0, 30, 3, 0, "0xD4", 4], "Output": {"Name": ["B30_D03_F0_0xd4"]}},
              {"Params": ["Target", 0, 30, 3, 1, "0xA8", 8], "Output": {"Name": ["B30_D03_F1_0xa8"]}},
              {"Params": ["Target", 0, 30, 3, 1, "0x108", 4], "Output": {"Name": ["B30_D03_F1_0x108"]}},
              {"Params": ["Target", 0, 30, 3, 1, "0x10C", 4], "Output": {"Name": ["B30_D03_F1_0x10c"]}},
              {"Params": ["Target", 0, 30, 3, 1, "0x110", 4], "Output": {"Name": ["B30_D03_F1_0x110"]}},
              {"Params": ["Target", 0, 30, 3, 1, "0x114", 4], "Output": {"Name": ["B30_D03_F1_0x114"]}},
              {"Params": ["Target", 0, 30, 3, 1, "0x118", 4], "Output": {"Name": ["B30_D03_F1_0x118"]}},
              {"Params": ["Target", 0, 30, 3, 1, "0x11C", 4], "Output": {"Name": ["B30_D03_F1_0x11c"]}},
              {"Params": ["Target", 0, 30, 4, 0, "0xD4", 4], "Output": {"Name": ["B30_D04_F0_0xd4"]}}
            ]
          }
        ]
      }
    },
    {
      "Uncore_MMIO": {
        "RecordEnable": true,
        "SkipOnFail": false,
        "LoopOnCPU": true,
        "MaxTimeSec": 30,
        "OutputPath": "crash_data/PROCESSORS/cpu%d/uncore",
        "PreReq": {
          "PECICmds": [
            {
              "RdEndpointConfigPCILocal": [
                {"Params": ["Target", 0, 8, 3, 0, "0x1A0", 4],"Output": {"Name": ["cpubusno_valid"]}, "InternalVar": "CPUBusNumValid"},
                {"Params": ["Target", 0, 8, 3, 0, "0x1CC", 4],"Output": {"Name": ["cpubusno7"]}, "InternalVar": "CPUBusNum7"},
                {"Params": ["Target", 0, 8, 3, 0, "0x198", 4],"Output": {"Name": ["cpubusno2"]}, "InternalVar": "CPUBusNum2"}
              ]
            },
            {
              "RdPostEnumBus": [
                {"Params": ["CPUBusNumValid", "CPUBusNum7", 30, 16],"Output": {"Name": ["post_enum_bus30"]}, "InternalVar": "PostEnumBus30",
                  "comment": "if CPUBusNumValid bit 30 is 1, then PostEnumBus30 = ((CPUBusNum7 >> 16) & 0xff)"},
                {"Params": ["CPUBusNumValid", "CPUBusNum2", 8, 0],"Output": {"Name": ["post_enum_bus8"]}, "InternalVar": "PostEnumBus8",
                  "comment": "if CPUBusNumValid bit 8 is 1, then PostEnumBus8 = ((CPUBusNum2 >> 0) & 0xff)"},
                {"Params": ["CPUBusNumValid", "CPUBusNum2", 9, 8],"Output": {"Name": ["post_enum_bus9"]}, "InternalVar": "PostEnumBus9",
                  "comment": "if CPUBusNumValid bit 9 is 1, then PostEnumBus9 = ((CPUBusNum2 >> 8) & 0xff)"},
                {"Params": ["CPUBusNumValid", "CPUBusNum2", 10, 16],"Output": {"Name": ["post_enum_bus10"]}, "InternalVar": "PostEnumBus10",
                  "comment": "if CPUBusNumValid bit 10 is 1, then PostEnumBus10 = ((CPUBusNum2 >> 16) & 0xff)"},
                {"Params": ["CPUBusNumValid", "CPUBusNum2", 11, 24],"Output": {"Name": ["post_enum_bus11"]}, "InternalVar": "PostEnumBus11",
                  "comment": "if CPUBusNumValid bit 11 is 1, then PostEnumBus11 = ((CPUBusNum2 >> 24) & 0xff)"}
              ]
            }
          ]
        },
        "PECICmds": [
          {
            "RdEndpointConfigMMIO": [
              {"Params": ["Target", 0, "PostEnumBus8", 1, 0, 0, 6, "0x90", 4], "Output": {"Name": ["B08_D01_F0_0x90"]}},
              {"Params": ["Target", 0, "PostEnumBus8", 1, 0, 0, 6, "0xc0", 8], "Output": {"Name": ["B08_D01_F0_0xc0"]}},
              {"Params": ["Target", 0, "PostEnumBus9", 1, 0, 0, 6, "0x90", 4], "Output": {"Name": ["B09_D01_F0_0x90"]}},
              {"Params": ["Target", 0, "PostEnumBus9", 1, 0, 0, 6, "0xc0", 8], "Output": {"Name": ["B09_D01_F0_0xc0"]}},
              {"Params": ["Target", 0, "PostEnumBus10", 1, 0, 0, 6, "0x90", 4], "Output": {"Name": ["B10_D01_F0_0x90"]}},
              {"Params": ["Target", 0, "PostEnumBus10", 1, 0, 0, 6, "0xc0", 8], "Output": {"Name": ["B10_D01_F0_0xc0"]}},
              {"Params": ["Target", 0, "PostEnumBus11", 1, 0, 0, 6, "0x90", 4], "Output": {"Name": ["B11_D01_F0_0x90"]}},
              {"Params": ["Target", 0, "PostEnumBus11", 1, 0, 0, 6, "0xc0", 8], "Output": {"Name": ["B11_D01_F0_0xc0"]}},
              {"Params": ["Target", 0, "PostEnumBus30", 26, 0, 0, 6, "0x20150", 4], "Output": {"Name": ["B30_D26_F0_0x20150"]}},
              {"Params": ["Target", 0, "PostEnumBus30", 26, 0, 0, 6, "0x2080C", 4], "Output": {"Name": ["B30_D26_F0_0x2080c"]}},
              {"Params": ["Target", 0, "PostEnumBus30", 26, 0, 0, 6, "0x20810", 4], "Output": {"Name": ["B30_D26_F0_0x20810"]}},
              {"Params": ["Target", 0, "PostEnumBus30", 26, 0, 0, 6, "0x20968", 4], "Output": {"Name": ["B30_D26_F0_0x20968"]}},
              {"Params": ["Target", 0, "PostEnumBus30", 26, 0, 0, 6, "0x21500", 8], "Output": {"Name": ["B30_D26_F0_0x21500"]}},
              {"Params": ["Target", 0, "PostEnumBus30", 26, 0, 0, 6, "0x21550", 4], "Output": {"Name": ["B30_D26_F0_0x21550"]}},
              {"Params": ["Target", 0, "PostEnumBus30", 26, 0, 0, 6, "0x22C18", 4], "Output": {"Name": ["B30_D26_F0_0x22c18"]}},
              {"Params": ["Target", 0, "PostEnumBus30", 26, 0, 0, 6, "0x22C1C", 4], "Output": {"Name": ["B30_D26_F0_0x22c1c"]}},
              {"Params": ["Target", 0, "PostEnumBus30", 26, 0, 0, 6, "0x22C20", 4], "Output": {"Name": ["B30_D26_F0_0x22c20"]}},
              {"Params": ["Target", 0, "PostEnumBus30", 26, 0, 0, 6, "0x22C24", 4], "Output": {"Name": ["B30_D26_F0_0x22c24"]}},
              {"Params": ["Target", 0, "PostEnumBus30", 26, 0, 0, 6, "0x22C50", 4], "Output": {"Name": ["B30_D26_F0_0x22c50"]}},
              {"Params": ["Target", 0, "PostEnumBus30", 26, 0, 0, 6, "0x22C60", 4], "Output": {"Name": ["B30_D26_F0_0x22c60"]}},
              {"Params": ["Target", 0, "PostEnumBus30", 26, 0, 0, 6, "0x23410", 4], "Output": {"Name": ["B30_D26_F0_0x23410"]}},
              {"Params": ["Target", 0, "PostEnumBus30", 26, 0, 0, 6, "0x23430", 8], "Output": {"Name": ["B30_D26_F0_0x23430"]}},
              {"Params": ["Target", 0, "PostEnumBus30", 26, 0, 0, 6, "0x23460", 4], "Output": {"Name": ["B30_D26_F0_0x23460"]}},
              {"Params": ["Target", 0, "PostEnumBus30", 26, 0, 0, 6, "0x28150", 4], "Output": {"Name": ["B30_D26_F0_0x28150"]}},
              {"Params": ["Target", 0, "PostEnumBus30", 26, 0, 0, 6, "0x2880C", 4], "Output": {"Name": ["B30_D26_F0_0x2880c"]}},
              {"Params": ["Target", 0, "PostEnumBus30", 26, 0, 0, 6, "0x28810", 4], "Output": {"Name": ["B30_D26_F0_0x28810"]}},
              {"Params": ["Target", 0, "PostEnumBus30", 26, 0, 0, 6, "0x28968", 4], "Output": {"Name": ["B30_D26_F0_0x28968"]}},
              {"Params": ["Target", 0, "PostEnumBus30", 26, 0, 0, 6, "0x29500", 8], "Output": {"Name": ["B30_D26_F0_0x29500"]}},
              {"Params": ["Target", 0, "PostEnumBus30", 26, 0, 0, 6, "0x29550", 4], "Output": {"Name": ["B30_D26_F0_0x29550"]}},
              {"Params": ["Target", 0, "PostEnumBus30", 26, 0, 0, 6, "0x2AC18", 4], "Output": {"Name": ["B30_D26_F0_0x2ac18"]}},
              {"Params": ["Target", 0, "PostEnumBus30", 26, 0, 0, 6, "0x2AC1C", 4], "Output": {"Name": ["B30_D26_F0_0x2ac1c"]}},
              {"Params": ["Target", 0, "PostEnumBus30", 26, 0, 0, 6, "0x2AC20", 4], "Output": {"Name": ["B30_D26_F0_0x2ac20"]}},
              {"Params": ["Target", 0, "PostEnumBus30", 26, 0, 0, 6, "0x2AC24", 4], "Output": {"Name": ["B30_D26_F0_0x2ac24"]}},
              {"Params": ["Target", 0, "PostEnumBus30", 26, 0, 0, 6, "0x2AC50", 4], "Output": {"Name": ["B30_D26_F0_0x2ac50"]}},
              {"Params": ["Target", 0, "PostEnumBus30", 26, 0, 0, 6, "0x2AC60", 4], "Output": {"Name": ["B30_D26_F0_0x2ac60"]}},
              {"Params": ["Target", 0, "PostEnumBus30", 26, 0, 0, 6, "0x2B410", 4], "Output": {"Name": ["B30_D26_F0_0x2b410"]}},
              {"Params": ["Target", 0, "PostEnumBus30", 26, 0, 0, 6, "0x2B430", 8], "Output": {"Name": ["B30_D26_F0_0x2b430"]}},
              {"Params": ["Target", 0, "PostEnumBus30", 27, 0, 0, 6, "0x20150", 4], "Output": {"Name": ["B30_D27_F0_0x20150"]}},
              {"Params": ["Target", 0, "PostEnumBus30", 27, 0, 0, 6, "0x2080C", 4], "Output": {"Name": ["B30_D27_F0_0x2080c"]}},
              {"Params": ["Target", 0, "PostEnumBus30", 27, 0, 0, 6, "0x20810", 4], "Output": {"Name": ["B30_D27_F0_0x20810"]}},
              {"Params": ["Target", 0, "PostEnumBus30", 27, 0, 0, 6, "0x20968", 4], "Output": {"Name": ["B30_D27_F0_0x20968"]}},
              {"Params": ["Target", 0, "PostEnumBus30", 27, 0, 0, 6, "0x21500", 8], "Output": {"Name": ["B30_D27_F0_0x21500"]}},
              {"Params": ["Target", 0, "PostEnumBus30", 27, 0, 0, 6, "0x21550", 4], "Output": {"Name": ["B30_D27_F0_0x21550"]}},
              {"Params": ["Target", 0, "PostEnumBus30", 27, 0, 0, 6, "0x22C18", 4], "Output": {"Name": ["B30_D27_F0_0x22c18"]}},
              {"Params": ["Target", 0, "PostEnumBus30", 27, 0, 0, 6, "0x22C1C", 4], "Output": {"Name": ["B30_D27_F0_0x22c1c"]}},
              {"Params": ["Target", 0, "PostEnumBus30", 27, 0, 0, 6, "0x22C20", 4], "Output": {"Name": ["B30_D27_F0_0x22c20"]}},
              {"Params": ["Target", 0, "PostEnumBus30", 27, 0, 0, 6, "0x22C24", 4], "Output": {"Name": ["B30_D27_F0_0x22c24"]}},
              {"Params": ["Target", 0, "PostEnumBus30", 27, 0, 0, 6, "0x22C50", 4], "Output": {"Name": ["B30_D27_F0_0x22c50"]}},
              {"Params": ["Target", 0, "PostEnumBus30", 27, 0, 0, 6, "0x22C60", 4], "Output": {"Name": ["B30_D27_F0_0x22c60"]}},
              {"Params": ["Target", 0, "PostEnumBus30", 27, 0, 0, 6, "0x23410", 4], "Output": {"Name": ["B30_D27_F0_0x23410"]}},
              {"Params": ["Target", 0, "PostEnumBus30", 27, 0, 0, 6, "0x23430", 8], "Output": {"Name": ["B30_D27_F0_0x23430"]}},
              {"Params": ["Target", 0, "PostEnumBus30", 27, 0, 0, 6, "0x28150", 4], "Output": {"Name": ["B30_D27_F0_0x28150"]}},
              {"Params": ["Target", 0, "PostEnumBus30", 27, 0, 0, 6, "0x2880C", 4], "Output": {"Name": ["B30_D27_F0_0x2880c"]}},
              {"Params": ["Target", 0, "PostEnumBus30", 27, 0, 0, 6, "0x28810", 4], "Output": {"Name": ["B30_D27_F0_0x28810"]}},
              {"Params": ["Target", 0, "PostEnumBus30", 27, 0, 0, 6, "0x28968", 4], "Output": {"Name": ["B30_D27_F0_0x28968"]}},
              {"Params": ["Target", 0, "PostEnumBus30", 27, 0, 0, 6, "0x29500", 8], "Output": {"Name": ["B30_D27_F0_0x29500"]}},
              {"Params": ["Target", 0, "PostEnumBus30", 27, 0, 0, 6, "0x29550", 4], "Output": {"Name": ["B30_D27_F0_0x29550"]}},
              {"Params": ["Target", 0, "PostEnumBus30", 27, 0, 0, 6, "0x2AC18", 4], "Output": {"Name": ["B30_D27_F0_0x2ac18"]}},
              {"Params": ["Target", 0, "PostEnumBus30", 27, 0, 0, 6, "0x2AC1C", 4], "Output": {"Name": ["B30_D27_F0_0x2ac1c"]}},
              {"Params": ["Target", 0, "PostEnumBus30", 27, 0, 0, 6, "0x2AC20", 4], "Output": {"Name": ["B30_D27_F0_0x2ac20"]}},
              {"Params": ["Target", 0, "PostEnumBus30", 27, 0, 0, 6, "0x2AC24", 4], "Output": {"Name": ["B30_D27_F0_0x2ac24"]}},
              {"Params": ["Target", 0, "PostEnumBus30", 27, 0, 0, 6, "0x2AC50", 4], "Output": {"Name": ["B30_D27_F0_0x2ac50"]}},
              {"Params": ["Target", 0, "PostEnumBus30", 27, 0, 0, 6, "0x2AC60", 4], "Output": {"Name": ["B30_D27_F0_0x2ac60"]}},
              {"Params": ["Target", 0, "PostEnumBus30", 27, 0, 0, 6, "0x2B410", 4], "Output": {"Name": ["B30_D27_F0_0x2b410"]}},
              {"Params": ["Target", 0, "PostEnumBus30", 27, 0, 0, 6, "0x2B430", 8], "Output": {"Name": ["B30_D27_F0_0x2b430"]}},
              {"Params": ["Target", 0, "PostEnumBus30", 28, 0, 0, 6, "0x20150", 4], "Output": {"Name": ["B30_D28_F0_0x20150"]}},
              {"Params": ["Target", 0, "PostEnumBus30", 28, 0, 0, 6, "0x2080C", 4], "Output": {"Name": ["B30_D28_F0_0x2080c"]}},
              {"Params": ["Target", 0, "PostEnumBus30", 28, 0, 0, 6, "0x20810", 4], "Output": {"Name": ["B30_D28_F0_0x20810"]}},
              {"Params": ["Target", 0, "PostEnumBus30", 28, 0, 0, 6, "0x20968", 4], "Output": {"Name": ["B30_D28_F0_0x20968"]}},
              {"Params": ["Target", 0, "PostEnumBus30", 28, 0, 0, 6, "0x21500", 8], "Output": {"Name": ["B30_D28_F0_0x21500"]}},
              {"Params": ["Target", 0, "PostEnumBus30", 28, 0, 0, 6, "0x21550", 4], "Output": {"Name": ["B30_D28_F0_0x21550"]}},
              {"Params": ["Target", 0, "PostEnumBus30", 28, 0, 0, 6, "0x22C18", 4], "Output": {"Name": ["B30_D28_F0_0x22c18"]}},
              {"Params": ["Target", 0, "PostEnumBus30", 28, 0, 0, 6, "0x22C1C", 4], "Output": {"Name": ["B30_D28_F0_0x22c1c"]}},
              {"Params": ["Target", 0, "PostEnumBus30", 28, 0, 0, 6, "0x22C20", 4], "Output": {"Name": ["B30_D28_F0_0x22c20"]}},
              {"Params": ["Target", 0, "PostEnumBus30", 28, 0, 0, 6, "0x22C24", 4], "Output": {"Name": ["B30_D28_F0_0x22c24"]}},
              {"Params": ["Target", 0, "PostEnumBus30", 28, 0, 0, 6, "0x22C50", 4], "Output": {"Name": ["B30_D28_F0_0x22c50"]}},
              {"Params": ["Target", 0, "PostEnumBus30", 28, 0, 0, 6, "0x22C60", 4], "Output": {"Name": ["B30_D28_F0_0x22c60"]}},
              {"Params": ["Target", 0, "PostEnumBus30", 28, 0, 0, 6, "0x23410", 4], "Output": {"Name": ["B30_D28_F0_0x23410"]}},
              {"Params": ["Target", 0, "PostEnumBus30", 28, 0, 0, 6, "0x23430", 8], "Output": {"Name": ["B30_D28_F0_0x23430"]}},
              {"Params": ["Target", 0, "PostEnumBus30", 28, 0, 0, 6, "0x28150", 4], "Output": {"Name": ["B30_D28_F0_0x28150"]}},
              {"Params": ["Target", 0, "PostEnumBus30", 28, 0, 0, 6, "0x2880C", 4], "Output": {"Name": ["B30_D28_F0_0x2880c"]}},
              {"Params": ["Target", 0, "PostEnumBus30", 28, 0, 0, 6, "0x28810", 4], "Output": {"Name": ["B30_D28_F0_0x28810"]}},
              {"Params": ["Target", 0, "PostEnumBus30", 28, 0, 0, 6, "0x28968", 4], "Output": {"Name": ["B30_D28_F0_0x28968"]}},
              {"Params": ["Target", 0, "PostEnumBus30", 28, 0, 0, 6, "0x29500", 8], "Output": {"Name": ["B30_D28_F0_0x29500"]}},
              {"Params": ["Target", 0, "PostEnumBus30", 28, 0, 0, 6, "0x29550", 4], "Output": {"Name": ["B30_D28_F0_0x29550"]}},
              {"Params": ["Target", 0, "PostEnumBus30", 28, 0, 0, 6, "0x2AC18", 4], "Output": {"Name": ["B30_D28_F0_0x2ac18"]}},
              {"Params": ["Target", 0, "PostEnumBus30", 28, 0, 0, 6, "0x2AC1C", 4], "Output": {"Name": ["B30_D28_F0_0x2ac1c"]}},
              {"Params": ["Target", 0, "PostEnumBus30", 28, 0, 0, 6, "0x2AC20", 4], "Output": {"Name": ["B30_D28_F0_0x2ac20"]}},
              {"Params": ["Target", 0, "PostEnumBus30", 28, 0, 0, 6, "0x2AC24", 4], "Output": {"Name": ["B30_D28_F0_0x2ac24"]}},
              {"Params": ["Target", 0, "PostEnumBus30", 28, 0, 0, 6, "0x2AC50", 4], "Output": {"Name": ["B30_D28_F0_0x2ac50"]}},
              {"Params": ["Target", 0, "PostEnumBus30", 28, 0, 0, 6, "0x2AC60", 4], "Output": {"Name": ["B30_D28_F0_0x2ac60"]}},
              {"Params": ["Target", 0, "PostEnumBus30", 28, 0, 0, 6, "0x2B410", 4], "Output": {"Name": ["B30_D28_F0_0x2b410"]}},
              {"Params": ["Target", 0, "PostEnumBus30", 28, 0, 0, 6, "0x2B430", 8], "Output": {"Name": ["B30_D28_F0_0x2b430"]}},
              {"Params": ["Target", 0, "PostEnumBus30", 29, 0, 0, 6, "0x20150", 4], "Output": {"Name": ["B30_D29_F0_0x20150"]}},
              {"Params": ["Target", 0, "PostEnumBus30", 29, 0, 0, 6, "0x2080C", 4], "Output": {"Name": ["B30_D29_F0_0x2080c"]}},
              {"Params": ["Target", 0, "PostEnumBus30", 29, 0, 0, 6, "0x20810", 4], "Output": {"Name": ["B30_D29_F0_0x20810"]}},
              {"Params": ["Target", 0, "PostEnumBus30", 29, 0, 0, 6, "0x20968", 4], "Output": {"Name": ["B30_D29_F0_0x20968"]}},
              {"Params": ["Target", 0, "PostEnumBus30", 29, 0, 0, 6, "0x21500", 8], "Output": {"Name": ["B30_D29_F0_0x21500"]}},
              {"Params": ["Target", 0, "PostEnumBus30", 29, 0, 0, 6, "0x21550", 4], "Output": {"Name": ["B30_D29_F0_0x21550"]}},
              {"Params": ["Target", 0, "PostEnumBus30", 29, 0, 0, 6, "0x22C18", 4], "Output": {"Name": ["B30_D29_F0_0x22c18"]}},
              {"Params": ["Target", 0, "PostEnumBus30", 29, 0, 0, 6, "0x22C1C", 4], "Output": {"Name": ["B30_D29_F0_0x22c1c"]}},
              {"Params": ["Target", 0, "PostEnumBus30", 29, 0, 0, 6, "0x22C20", 4], "Output": {"Name": ["B30_D29_F0_0x22c20"]}},
              {"Params": ["Target", 0, "PostEnumBus30", 29, 0, 0, 6, "0x22C24", 4], "Output": {"Name": ["B30_D29_F0_0x22c24"]}},
              {"Params": ["Target", 0, "PostEnumBus30", 29, 0, 0, 6, "0x22C50", 4], "Output": {"Name": ["B30_D29_F0_0x22c50"]}},
              {"Params": ["Target", 0, "PostEnumBus30", 29, 0, 0, 6, "0x22C60", 4], "Output": {"Name": ["B30_D29_F0_0x22c60"]}},
              {"Params": ["Target", 0, "PostEnumBus30", 29, 0, 0, 6, "0x23410", 4], "Output": {"Name": ["B30_D29_F0_0x23410"]}},
              {"Params": ["Target", 0, "PostEnumBus30", 29, 0, 0, 6, "0x23430", 8], "Output": {"Name": ["B30_D29_F0_0x23430"]}},
              {"Params": ["Target", 0, "PostEnumBus30", 29, 0, 0, 6, "0x28150", 4], "Output": {"Name": ["B30_D29_F0_0x28150"]}},
              {"Params": ["Target", 0, "PostEnumBus30", 29, 0, 0, 6, "0x2880C", 4], "Output": {"Name": ["B30_D29_F0_0x2880c"]}},
              {"Params": ["Target", 0, "PostEnumBus30", 29, 0, 0, 6, "0x28810", 4], "Output": {"Name": ["B30_D29_F0_0x28810"]}},
              {"Params": ["Target", 0, "PostEnumBus30", 29, 0, 0, 6, "0x28968", 4], "Output": {"Name": ["B30_D29_F0_0x28968"]}},
              {"Params": ["Target", 0, "PostEnumBus30", 29, 0, 0, 6, "0x29500", 8], "Output": {"Name": ["B30_D29_F0_0x29500"]}},
              {"Params": ["Target", 0, "PostEnumBus30", 29, 0, 0, 6, "0x29550", 4], "Output": {"Name": ["B30_D29_F0_0x29550"]}},
              {"Params": ["Target", 0, "PostEnumBus30", 29, 0, 0, 6, "0x2AC18", 4], "Output": {"Name": ["B30_D29_F0_0x2ac18"]}},
              {"Params": ["Target", 0, "PostEnumBus30", 29, 0, 0, 6, "0x2AC1C", 4], "Output": {"Name": ["B30_D29_F0_0x2ac1c"]}},
              {"Params": ["Target", 0, "PostEnumBus30", 29, 0, 0, 6, "0x2AC20", 4], "Output": {"Name": ["B30_D29_F0_0x2ac20"]}},
              {"Params": ["Target", 0, "PostEnumBus30", 29, 0, 0, 6, "0x2AC24", 4], "Output": {"Name": ["B30_D29_F0_0x2ac24"]}},
              {"Params": ["Target", 0, "PostEnumBus30", 29, 0, 0, 6, "0x2AC50", 4], "Output": {"Name": ["B30_D29_F0_0x2ac50"]}},
              {"Params": ["Target", 0, "PostEnumBus30", 29, 0, 0, 6, "0x2AC60", 4], "Output": {"Name": ["B30_D29_F0_0x2ac60"]}},
              {"Params": ["Target", 0, "PostEnumBus30", 29, 0, 0, 6, "0x2B410", 4], "Output": {"Name": ["B30_D29_F0_0x2b410"]}},
              {"Params": ["Target", 0, "PostEnumBus30", 29, 0, 0, 6, "0x2B430", 8], "Output": {"Name": ["B30_D29_F0_0x2b430"]}},
              {"Params": ["Target", 0, "PostEnumBus30", 26, 0, 0, 6, "0x21A2C", 4], "Output": {"Name": ["B30_D26_F0_0x21a2c"]}},
              {"Params": ["Target", 0, "PostEnumBus30", 26, 0, 0, 6, "0x21A30", 4], "Output": {"Name": ["B30_D26_F0_0x21a30"]}},
              {"Params": ["Target", 0, "PostEnumBus30", 26, 0, 0, 6, "0x2290", 8], "Output": {"Name": ["B30_D26_F0_0x2290"]}},
              {"Params": ["Target", 0, "PostEnumBus30", 26, 0, 0, 6, "0x2298", 8], "Output": {"Name": ["B30_D26_F0_0x2298"]}},
              {"Params": ["Target", 0, "PostEnumBus30", 26, 0, 0, 6, "0x22A0", 8], "Output": {"Name": ["B30_D26_F0_0x22a0"]}},
              {"Params": ["Target", 0, "PostEnumBus30", 26, 0, 0, 6, "0x22A8", 8], "Output": {"Name": ["B30_D26_F0_0x22a8"]}},
              {"Params": ["Target", 0, "PostEnumBus30", 26, 0, 0, 6, "0x29A2C", 4], "Output": {"Name": ["B30_D26_F0_0x29a2c"]}},
              {"Params": ["Target", 0, "PostEnumBus30", 26, 0, 0, 6, "0x29A30", 4], "Output": {"Name": ["B30_D26_F0_0x29a30"]}},
              {"Params": ["Target", 0, "PostEnumBus30", 27, 0, 0, 6, "0x21A2C", 4], "Output": {"Name": ["B30_D27_F0_0x21a2c"]}},
              {"Params": ["Target", 0, "PostEnumBus30", 27, 0, 0, 6, "0x21A30", 4], "Output": {"Name": ["B30_D27_F0_0x21a30"]}},
              {"Params": ["Target", 0, "PostEnumBus30", 27, 0, 0, 6, "0x2290", 8], "Output": {"Name": ["B30_D27_F0_0x2290"]}},
              {"Params": ["Target", 0, "PostEnumBus30", 27, 0, 0, 6, "0x2298", 8], "Output": {"Name": ["B30_D27_F0_0x2298"]}},
              {"Params": ["Target", 0, "PostEnumBus30", 27, 0, 0, 6, "0x22A0", 8], "Output": {"Name": ["B30_D27_F0_0x22a0"]}},
              {"Params": ["Target", 0, "PostEnumBus30", 27, 0, 0, 6, "0x22A8", 8], "Output": {"Name": ["B30_D27_F0_0x22a8"]}},
              {"Params": ["Target", 0, "PostEnumBus30", 27, 0, 0, 6, "0x29A2C", 4], "Output": {"Name": ["B30_D27_F0_0x29a2c"]}},
              {"Params": ["Target", 0, "PostEnumBus30", 27, 0, 0, 6, "0x29A30", 4], "Output": {"Name": ["B30_D27_F0_0x29a30"]}},
              {"Params": ["Target", 0, "PostEnumBus30", 28, 0, 0, 6, "0x21A2C", 4], "Output": {"Name": ["B30_D28_F0_0x21a2c"]}},
              {"Params": ["Target", 0, "PostEnumBus30", 28, 0, 0, 6, "0x21A30", 4], "Output": {"Name": ["B30_D28_F0_0x21a30"]}},
              {"Params": ["Target", 0, "PostEnumBus30", 28, 0, 0, 6, "0x2290", 8], "Output": {"Name": ["B30_D28_F0_0x2290"]}},
              {"Params": ["Target", 0, "PostEnumBus30", 28, 0, 0, 6, "0x2298", 8], "Output": {"Name": ["B30_D28_F0_0x2298"]}},
              {"Params": ["Target", 0, "PostEnumBus30", 28, 0, 0, 6, "0x22A0", 8], "Output": {"Name": ["B30_D28_F0_0x22a0"]}},
              {"Params": ["Target", 0, "PostEnumBus30", 28, 0, 0, 6, "0x22A8", 8], "Output": {"Name": ["B30_D28_F0_0x22a8"]}},
              {"Params": ["Target", 0, "PostEnumBus30", 28, 0, 0, 6, "0x29A2C", 4], "Output": {"Name": ["B30_D28_F0_0x29a2c"]}},
              {"Params": ["Target", 0, "PostEnumBus30", 28, 0, 0, 6, "0x29A30", 4], "Output": {"Name": ["B30_D28_F0_0x29a30"]}},
              {"Params": ["Target", 0, "PostEnumBus30", 29, 0, 0, 6, "0x21A2C", 4], "Output": {"Name": ["B30_D29_F0_0x21a2c"]}},
              {"Params": ["Target", 0, "PostEnumBus30", 29, 0, 0, 6, "0x21A30", 4], "Output": {"Name": ["B30_D29_F0_0x21a30"]}},
              {"Params": ["Target", 0, "PostEnumBus30", 29, 0, 0, 6, "0x2290", 8], "Output": {"Name": ["B30_D29_F0_0x2290"]}},
              {"Params": ["Target", 0, "PostEnumBus30", 29, 0, 0, 6, "0x2298", 8], "Output": {"Name": ["B30_D29_F0_0x2298"]}},
              {"Params": ["Target", 0, "PostEnumBus30", 29, 0, 0, 6, "0x22A0", 8], "Output": {"Name": ["B30_D29_F0_0x22a0"]}},
              {"Params": ["Target", 0, "PostEnumBus30", 29, 0, 0, 6, "0x22A8", 8], "Output": {"Name": ["B30_D29_F0_0x22a8"]}},
              {"Params": ["Target", 0, "PostEnumBus30", 29, 0, 0, 6, "0x29A2C", 4], "Output": {"Name": ["B30_D29_F0_0x29a2c"]}},
              {"Params": ["Target", 0, "PostEnumBus30", 29, 0, 0, 6, "0x29A30", 4], "Output": {"Name": ["B30_D29_F0_0x29a30"]}}
            ]
          }
        ]
      }
    },
    {
      "Uncore_RdIAMSR": {
        "RecordEnable": true,
        "SkipOnFail": false,
        "LoopOnCPU": true,
        "MaxTimeSec": 30,
        "OutputPath": "crash_data/PROCESSORS/cpu%d/uncore",
        "PreReq": {
          "PECICmds": []
        },
        "PECICmds": [
          {
            "RdIAMSR": [
              {"Params": ["Target", 0, "0x1b1"], "Output": {"Size": 4,"Name": ["RDIAMSR_0x1b1"]}},
              {"Params": ["Target", 0, "0x613"], "Output": {"Size": 4,"Name": ["RDIAMSR_0x613"]}},
              {"Params": ["Target", 0, "0x619"], "Output": {"Size": 4,"Name": ["RDIAMSR_0x619"]}},
              {"Params": ["Target", 0, "0x621"], "Output": {"Size": 4,"Name": ["RDIAMSR_0x621"]}},
              {"Params": ["Target", 0, "0x64f"], "Output": {"Size": 4,"Name": ["RDIAMSR_0x64f"]}},
              {"Params": ["Target", 0, "0x8017"], "Output": {"Size": 4,"Name": ["RDIAMSR_mdfh0_0x8017"]}},
              {"Params": ["Target", 1, "0x8017"], "Output": {"Size": 4,"Name": ["RDIAMSR_mdfh1_0x8017"]}},
              {"Params": ["Target", 1, "0x8018"], "Output": {"Size": 4,"Name": ["RDIAMSR_mdfh1_0x8018"]}},
              {"Params": ["Target", 0, "0x8017"], "Output": {"Size": 4,"Name": ["RDIAMSR_mdfv0_0x8017"]}},
              {"Params": ["Target", 0, "0x82a0"], "Output": {"Size": 4,"Name": ["RDIAMSR_mdfh0_0x82a0"]}},
              {"Params": ["Target", 1, "0x82a0"], "Output": {"Size": 4,"Name": ["RDIAMSR_mdfh1_0x82a0"]}},
              {"Params": ["Target", 2, "0x82a0"], "Output": {"Size": 4,"Name": ["RDIAMSR_mdfh2_0x82a0"]}},
              {"Params": ["Target", 3, "0x82a0"], "Output": {"Size": 4,"Name": ["RDIAMSR_mdfh3_0x82a0"]}},
              {"Params": ["Target", 4, "0x82a0"], "Output": {"Size": 4,"Name": ["RDIAMSR_mdfh4_0x82a0"]}},
              {"Params": ["Target", 5, "0x82a0"], "Output": {"Size": 4,"Name": ["RDIAMSR_mdfh5_0x82a0"]}},
              {"Params": ["Target", 6, "0x82a0"], "Output": {"Size": 4,"Name": ["RDIAMSR_mdfh6_0x82a0"]}},
              {"Params": ["Target", 7, "0x82a0"], "Output": {"Size": 4,"Name": ["RDIAMSR_mdfh7_0x82a0"]}},
              {"Params": ["Target", 8, "0x82a0"], "Output": {"Size": 4,"Name": ["RDIAMSR_mdfh8_0x82a0"]}},
              {"Params": ["Target", 9, "0x82a0"], "Output": {"Size": 4,"Name": ["RDIAMSR_mdfh9_0x82a0"]}},
              {"Params": ["Target", 10, "0x82a0"], "Output": {"Size": 4,"Name": ["RDIAMSR_mdfh10_0x82a0"]}},
              {"Params": ["Target", 11, "0x82a0"], "Output": {"Size": 4,"Name": ["RDIAMSR_mdfh11_0x82a0"]}},
              {"Params": ["Target", 12, "0x82a0"], "Output": {"Size": 4,"Name": ["RDIAMSR_mdfh12_0x82a0"]}},
              {"Params": ["Target", 13, "0x82a0"], "Output": {"Size": 4,"Name": ["RDIAMSR_mdfh13_0x82a0"]}},
              {"Params": ["Target", 14, "0x82a0"], "Output": {"Size": 4,"Name": ["RDIAMSR_mdfh14_0x82a0"]}},
              {"Params": ["Target", 15, "0x82a0"], "Output": {"Size": 4,"Name": ["RDIAMSR_mdfh15_0x82a0"]}},
              {"Params": ["Target", 16, "0x82a0"], "Output": {"Size": 4,"Name": ["RDIAMSR_mdfh16_0x82a0"]}},
              {"Params": ["Target", 17, "0x82a0"], "Output": {"Size": 4,"Name": ["RDIAMSR_mdfh17_0x82a0"]}},
              {"Params": ["Target", 18, "0x82a0"], "Output": {"Size": 4,"Name": ["RDIAMSR_mdfh18_0x82a0"]}},
              {"Params": ["Target", 19, "0x82a0"], "Output": {"Size": 4,"Name": ["RDIAMSR_mdfh19_0x82a0"]}},
              {"Params": ["Target", 20, "0x82a0"], "Output": {"Size": 4,"Name": ["RDIAMSR_mdfh20_0x82a0"]}},
              {"Params": ["Target", 21, "0x82a0"], "Output": {"Size": 4,"Name": ["RDIAMSR_mdfh21_0x82a0"]}},
              {"Params": ["Target", 22, "0x82a0"], "Output": {"Size": 4,"Name": ["RDIAMSR_mdfh22_0x82a0"]}},
              {"Params": ["Target", 23, "0x82a0"], "Output": {"Size": 4,"Name": ["RDIAMSR_mdfh23_0x82a0"]}},
              {"Params": ["Target", 0, "0x8208"], "Output": {"Size": 4,"Name": ["RDIAMSR_0x8208"]}}
            ]
          }
        ]
      }
    },
    {
      "Uncore_RdIAMSR_CHA": {
        "RecordEnable": false
      }
    },
    {
      "TOR": {
        "RecordEnable": false,
        "RootAtLevel": 4,
        "OutputPath": "crash_data/PROCESSORS/cpu%d/TOR"
      }
    },
    {
      "PowerManagement_PCI": {
        "RecordEnable": false,
        "RootAtLevel": 4,
        "OutputPath": "crash_data/PROCESSORS/cpu%d/PM_info"
      }
    },
    {
      "PowerManagement_PCI_core": {
        "RecordEnable": false
      }
    },
    {
      "PowerManagement_Pll": {
        "RecordEnable": false
      }
    },
    {
      "PowerManagement_Dispatcher": {
        "RecordEnable": false
      }
    },
    {
      "BigCore" : {
        "RecordEnable": false,
        "RootAtLevel": 4,
        "OutputPath": "crash_data/PROCESSORS/cpu%d/big_core"
      }
    },
    {
      "MCA_CORE": {
        "RecordEnable": false
      }
    },
    {
      "Metadata_Cpu": {
        "RecordEnable": true,
        "RecordType": "0xb",
        "ProductType": "0x6f",
        "Revision": "0x01",
        "SkipOnFail": false,
        "LoopOnCpu": true,
        "MaxTimeSec": 10,
        "RootAtLevel": 2,
        "OutputPath": "crash_data/METADATA/cpu%d",
        "PreReq": {
          "PECICmds": [
            {
              "RdPkgConfig": [
                {"Params": ["Target", 19, 1, 4], "InternalVar": "ppin_low"},
                {"Params": ["Target", 19, 2, 4], "InternalVar": "ppin_high"}
              ]
            },
            {
              "RdEndpointConfigPCILocal": [
                {"Params": ["Target", 0, 31, 30, 4, "0xF8", 4], "InternalVar": "firstierrtsc_low"},
                {"Params": ["Target", 0, 31, 30, 4, "0xFC", 4], "InternalVar": "firstierrtsc_high"},
                {"Params": ["Target", 0, 31, 30, 4, "0xF0", 4], "InternalVar": "firstmcerrtsc_low"},
                {"Params": ["Target", 0, 31, 30, 4, "0xF4", 4], "InternalVar": "firstmcerrtsc_high"},
                {"Params": ["Target", 0, 31, 30, 3, "0x9c", 4], "InternalVar": "chamask0"},
                {"Params": ["Target", 0, 31, 30, 3, "0xa0", 4], "InternalVar": "chamask1"}
              ]
            }
          ]
        },
        "PECICmds": [
          {
            "RdGlobalVars": [
              {"Params": ["peci_addr"], "Output": {"Name": ["peci_id"]}},
              {"Params": ["cpuid"], "Output": {"Name": ["cpuid"]}},
              {"Params": ["cpuid_source"], "Output": {"Name": ["_cpuid_source"]}},
              {"Params": ["coremask_source"], "Output": {"Name": ["_core_mask_source"]}},
              {"Params": ["chacount_source"], "Output": {"Name": ["_cha_count_source"]}},
              {"Params": ["coremask"], "Output": {"Name": ["core_mask"]}},
              {"Params": ["chacount"], "Output": {"Name": ["cha_count"]}},
              {"Params": ["corecount"], "Output": {"Name": ["core_count"]}},
              {"Params": ["crashcorecount"], "Output": {"Name": ["crashcore_count"]}},
              {"Params": ["crashcoremask"], "Output": {"Name": ["crashcore_mask"]}}
            ]
          },
          {
            "SaveStrVars":[
              {"Params":["N/A"],"Output":{"Name":["package_id"]}}
            ]
          },
          {
            "RdAndConcatenate": [
              {"Params": ["chamask0", "chamask1"], "Output": {"Size": 8,"Name": ["cha_mask"]}},
              {"Params": ["ppin_low", "ppin_high"], "Output": {"Size": 8,"Name": ["ppin"]}},
              {"Params": ["firstierrtsc_low", "firstierrtsc_high"], "Output": {"Size": 8,"Name": ["firstierrtsc"]}},
              {"Params": ["firstmcerrtsc_low", "firstmcerrtsc_high"], "Output": {"Size": 8,"Name": ["firstmcerrtsc"]}}
            ]
          },
          {
            "RdEndpointConfigPCILocal": [
              {"Params": ["Target", 0, 30, 0, 0, "0xA4", 4], "Output": {"Name": ["ierrloggingreg"]}},
              {"Params": ["Target", 0, 30, 0, 0, "0xA8", 4], "Output": {"Name": ["mcerrloggingreg"]}},
              {"Params": ["Target", 0, 31, 30, 2, "0xEC", 4], "Output": {"Name": ["mca_err_src_log"]}}
            ]
          },
          {
            "RdPkgConfig": [
              {"Params": ["Target", 0, 4, 4],"Output": {"Name":["ucode_patch_ver"]}},
              {"Params": ["Target", 0, 1, 4],"Output": {"Name":["platform_id"]}}
            ]
          }
        ]
      }
    },
    {
      "crashlog": {
        "RecordEnable": false,
        "RootAtLevel": 4,
        "OutputPath": "crash_data/PROCESSORS/cpu%d/crashlog"
      }
    }
  ]
}
